{
  "parent": "minecraft:recipes/root",
  "rewards": {
    "recipes": [
      "steamworld:shard_endritch_from_block"
    ]
  },
  "criteria": {
    "has_the_recipe": {
      "trigger": "minecraft:recipe_unlocked",
      "conditions": {
        "recipe": "steamworld:shard_endritch_from_block"
      }
    },
    "has_endritch_block": {
      "trigger": "minecraft:inventory_changed",
      "conditions": {
        "items": [
          {
            "item": "steamworld:block_decorative", "data": 0
          }
        ]
      }
    }
  },
  "requirements": [
    [
      "has_the_recipe",
      "has_endritch_block"
    ]
  ]
}